seqinfer/__init__.py
seqinfer/infer/__init__.py
seqinfer/infer/classifiers.py
seqinfer/infer/components/__init__.py
seqinfer/infer/components/architectures.py
seqinfer/infer/components/callbacks.py
seqinfer/infer/components/losses.py
seqinfer/infer/decoders.py
seqinfer/infer/encoders.py
seqinfer/infer/regressors.py
seqinfer/seq/__init__.py
seqinfer/seq/datasets.py
seqinfer/seq/transforms.py
seqinfer/seq/vocabularies.py
seqinfer/utils/__init__.py
seqinfer/utils/logger.py
seqinfer/utils/misc.py
seqinfer/utils/seq_utils.py
seqinfer-0.1.dev1.dist-info/LICENSE
seqinfer-0.1.dev1.dist-info/METADATA
seqinfer-0.1.dev1.dist-info/WHEEL
seqinfer-0.1.dev1.dist-info/RECORD
