Metadata-Version: 2.1
Name: seqinfer
Version: 0.1.dev1
Summary: A Python library for sequence inference.
License: MIT
Author: jjxiao
Author-email: jiajiexiao@users.noreply.github.com
Requires-Python: >=3.10,<4.0
Classifier: License :: OSI Approved :: MIT License
Classifier: Operating System :: OS Independent
Classifier: Programming Language :: Python :: 3
Classifier: Programming Language :: Python :: 3.10
Classifier: Programming Language :: Python :: 3.11
Requires-Dist: biopython (>=1.81,<2.0)
Requires-Dist: numpy (>=1.25.1,<2.0.0)
Requires-Dist: scikit-learn (>=1.3.0,<2.0.0)
Requires-Dist: torch (>=2.0.0,<3.0.0)
